{"letters":
  [{"letter":"a" ,
    "letterSrc": "assets/alphabet-buttons/a.png",
    "imgs":[
      {"src": ["assets/5/animals/wale.png",
                "assets/5/animals/snake.png"
              ],
       "name" : "A"
     },
     {"src": [
              "assets/5/animals/tiger.png"
     ],
      "name" : "e"
    },
    {"src": ["assets/5/animals/octopus.png",
              "assets/5/animals/frog.png",
              "assets/5/animals/dog.png",
              "assets/5/animals/lion.png"
            ],
     "name" : "o"
   }
      ]
    },
    {"letter":"e" ,
      "letterSrc": "assets/alphabet-buttons/e.png",
      "imgs":[
        {"src": [
                  "assets/5/animals/frog.png",
                  "assets/5/animals/dog.png",
                  "assets/5/animals/lion.png"
                ],
         "name" : "o"
       },
      {"src": [
              "assets/5/animals/sheep.png"
              ],
       "name" : "E"
     },
      {"src": ["assets/5/animals/octopus.png",
                "assets/5/animals/duck.png"
              ],
       "name" : "u"
     }
        ]
    },
    {"letter":"i" ,
      "letterSrc": "assets/alphabet-buttons/i.png",
      "imgs":[
       {"src": [ "assets/5/animals/horse.png",
                 "assets/5/animals/frog.png",
                 "assets/5/animals/dog.png"
                 ],
        "name" : "o"
      },
      {"src": ["assets/5/animals/octopus.png",
                "assets/5/animals/turtle.png",
                "assets/5/animals/duck.png"],
       "name" : "u"
     },
     {"src": ["assets/5/animals/aligator.png",
              "assets/5/animals/fish.png",
              "assets/5/animals/bird.png",
              "assets/5/animals/pig.png"],
      "name" : "I"
    }
        ]
    },
    {"letter":"o" ,
      "letterSrc": "assets/alphabet-buttons/o.png",
      "imgs":[
       {"src": [ "assets/5/animals/wale.png",
                 "assets/5/animals/snake.png"
                ],
        "name" : "a"
      },
      {"src": [
              "assets/5/animals/sheep.png"
            ],
       "name" : "e"
     },
     {"src": ["assets/5/animals/octopus.png",
               "assets/5/animals/frog.png",
               "assets/5/animals/horse.png",
               "assets/5/animals/dog.png"
             ],
      "name" : "o"
    }
        ]
    },
  {"letter":"u" ,
    "letterSrc": "assets/alphabet-buttons/u.png",
    "imgs":[
            {"src": [  "assets/5/animals/octopus.png",
                        "assets/5/animals/duck.png"
                    ],
             "name" : "u"
           },
           {"src": [
                   "assets/5/animals/sheep.png"
                  ],
            "name" : "e"
          },
          {"src": ["assets/5/animals/aligator.png",
                   "assets/5/animals/fish.png",
                   "assets/5/animals/bird.png",
                   "assets/5/animals/pig.png"],
           "name" : "I"
         }
      ]
    }
    ],
  "instructions": "Hi! Listen to the letter and then select the figure having the letter in its name. Good Luck!",
  "successMessages": ["Well done!", "Awesome!","Great!","Amazing!"],
  "errorMessages": ["Try again!"],
  "scoreSetUp" : {
    "add": 1,
    "substract": 1
  },
  "finalizationLevel": 3,
  "successFeedback": [
    {
      "path": "great.ogg",
      "text": "Great!"
    }
  ],
  "failureFeedback": [
    {
      "path": "try_again.ogg",
      "text": "Try again!"
    }
  ]
}
